infi.iscsiapi-0.2.13-py3.7-nspkg.pth
infi/iscsiapi/__init__.py
infi/iscsiapi/__version__.py
infi/iscsiapi/auth.py
infi/iscsiapi/base.py
infi/iscsiapi/iscsi_exceptions.py
infi/iscsiapi/linux.py
infi/iscsiapi/solaris.py
infi/iscsiapi/windows.py
infi.iscsiapi-0.2.13.dist-info/LICENSE
infi.iscsiapi-0.2.13.dist-info/METADATA
infi.iscsiapi-0.2.13.dist-info/WHEEL
infi.iscsiapi-0.2.13.dist-info/entry_points.txt
infi.iscsiapi-0.2.13.dist-info/namespace_packages.txt
infi.iscsiapi-0.2.13.dist-info/top_level.txt
infi.iscsiapi-0.2.13.dist-info/RECORD
