Metadata-Version: 2.1
Name: infi.iscsiapi
Version: 0.2.13
Summary: cross platfrom iSCSI opertions
Home-page: https://git.infinidat.com/host-opensource/infi.iscsiapi
Author: Arnon Yaari
Author-email: arnony@infinidat.com
License: BSD
Platform: UNKNOWN
Classifier: Intended Audience :: Developers
Classifier: Intended Audience :: System Administrators
Classifier: License :: OSI Approved :: BSD License
Classifier: Operating System :: OS Independent
Classifier: Programming Language :: Python :: 2
Classifier: Programming Language :: Python :: 3
Classifier: Topic :: Software Development :: Libraries :: Python Modules
Requires-Dist: infi.dtypes.hctl
Requires-Dist: infi.dtypes.iqn
Requires-Dist: infi.execute
Requires-Dist: infi.os-info
Requires-Dist: infi.pkgmgr
Requires-Dist: infi.win32service
Requires-Dist: infi.wmi
Requires-Dist: setuptools
Requires-Dist: six
